{
  "generatedAt": "2026-06-05T06:19:54.776Z",
  "source": {
    "note": "Dados gerados por script CI para evitar limite de rate no cliente",
    "tokenConfigured": true
  },
  "repositories": [
    {
      "owner": "DataCrash",
      "name": "datacrash.github.io",
      "stars": 0,
      "forks": 0,
      "openIssues": 0,
      "watchers": 0,
      "lastUpdatedAt": "2026-06-04T06:40:33Z"
    },
    {
      "owner": "DataCrash",
      "name": "professional-hub",
      "stars": 0,
      "forks": 0,
      "openIssues": 0,
      "watchers": 0,
      "lastUpdatedAt": "2026-06-04T06:48:07Z"
    },
    {
      "owner": "DataCrash",
      "name": "datacrash",
      "stars": 0,
      "forks": 0,
      "openIssues": 0,
      "watchers": 0,
      "lastUpdatedAt": "2026-06-04T15:34:52Z"
    }
  ]
}
